setup.cfg
setup.py
dist_alx/__init__.py
dist_alx/main.py
geolocationm.egg-info/PKG-INFO
geolocationm.egg-info/SOURCES.txt
geolocationm.egg-info/dependency_links.txt
geolocationm.egg-info/not-zip-safe
geolocationm.egg-info/top_level.txt