Metadata-Version: 1.0
Name: geolocationm
Version: 1
Summary: Get geolocation this user
Home-page: UNKNOWN
Author: UNKNOWN
Author-email: maksim9305s@gmail.com
License: UNKNOWN
Platform: UNKNOWN
